setup.cfg
setup.py
pyrsos/Model.py
pyrsos/Trainer.py
pyrsos/__init__.py
pyrsos/training.py
pyrsos.egg-info/PKG-INFO
pyrsos.egg-info/SOURCES.txt
pyrsos.egg-info/dependency_links.txt
pyrsos.egg-info/top_level.txt
pyrsos/logger/__init__.py
pyrsos/logger/experiment.py
pyrsos/logger/inspection.py
pyrsos/logger/plotting.py