Metadata-Version: 1.0
Name: pyrsos
Version: 0.2.2
Summary: PyTorch helper functions.
Home-page: https://github.com/cbaziotis/pyrsos
Author: Christos Baziotis
Author-email: christos.baziotis@gmail.com
License: MIT
Platform: UNKNOWN
